idk/__init__.py
idk/_cli.py
idk/_service.py
idk/_utils.py
idk/_version.py
idk/insight.py
idk/io.py
idk/templates/__init__.py
idk/templates/_gen_template.py
idk/templates/_tracking_template.py
idk/templates/_trans_template.py
cdl_idk-0.3.4.dist-info/METADATA
cdl_idk-0.3.4.dist-info/WHEEL
cdl_idk-0.3.4.dist-info/entry_points.txt
cdl_idk-0.3.4.dist-info/top_level.txt
cdl_idk-0.3.4.dist-info/RECORD
