Metadata-Version: 2.1
Name: cdl-idk
Version: 0.3.4
Summary: Tools for building insight generators
Home-page: UNKNOWN
Author: eden.trainor@compassdigital.io
License: UNKNOWN
Platform: UNKNOWN
Classifier: Development Status :: 4 - Beta
Classifier: Intended Audience :: Developers
Classifier: License :: OSI Approved :: Apache Software License
Classifier: Programming Language :: Python :: 3.8
Classifier: Topic :: Software Development :: Code Generators
Classifier: Topic :: Utilities
Requires-Python: >=3.6
Requires-Dist: requests
Requires-Dist: mypy
Requires-Dist: pandas
